README.md
setup.py
Code/PaRaVis.py
Code/__init__.py
aasasasaed.egg-info/PKG-INFO
aasasasaed.egg-info/SOURCES.txt
aasasasaed.egg-info/dependency_links.txt
aasasasaed.egg-info/requires.txt
aasasasaed.egg-info/top_level.txt